exenenv/__init__.py
exenenv/convertors.py
exenenv/env.py
exenenv/errors.py
exenenv-1.2.dist-info/METADATA
exenenv-1.2.dist-info/LICENSE
exenenv-1.2.dist-info/WHEEL
exenenv-1.2.dist-info/RECORD
