Metadata-Version: 2.1
Name: exenenv
Version: 1.2
Summary: Environment variables verifier and type converter.
Home-page: https://github.com/Exenifix/ExenENV
Author: Exenifix
Requires-Python: >=3.10,<4.0
Classifier: Programming Language :: Python :: 3
Classifier: Programming Language :: Python :: 3.10
Classifier: Programming Language :: Python :: 3.11
Project-URL: Repository, https://github.com/Exenifix/ExenENV
